3-inst-mips/toy-mips.v
module toy_processor (
    input wire clk,
    input wire reset
);

    // Define registers and memory
    // 32 registers, 256 bytes of memory (instruction and data)
    reg [31:0] rf [0:31];
    reg [31:0] inst_mem [0:63];
    reg [31:0] data_mem [0:63];

    // Program Counter
    reg [7:0] pc;

    // Instruction Fetch
    wire [31:0] instruction;
    assign instruction = inst_mem[pc];

    // Instruction Decode
    reg [5:0] opcode;
    reg [4:0] rs, rt, rd, shamt;
    reg [15:0] immediate;
    reg [25:0] address;
    reg [5:0] funct;

    always @ (posedge clk or posedge reset) begin
        if (reset) begin
            pc <= 0;
        end else begin
            opcode <= instruction[31:26];
            rs <= instruction[25:21];
            rt <= instruction[20:16];
            rd <= instruction[15:11];
            shamt <= instruction[10:6];
            immediate <= instruction[15:0];
            address <= instruction[25:0];
            funct <= instruction[5:0];

            // Increment PC by default, override for branches/jumps
            pc <= pc + 1;

            // Execute instructions
            case (opcode)
                6'b001001: begin // li $rt, immediate
                    rf[rt] <= {{16{immediate[15]}}, immediate};
                    $display("li $%-2d, %-d", rt, immediate);
                end
                6'b001000: begin // addi $rt, $rs, immediate
                    rf[rt] <= rf[rs] + immediate;
                    $display("addi $%-2d, $%-2d, %-d", rt, rs, immediate);
                end
                6'b100011: begin // lw $rt, offset($rs)
                    rf[rt] <= data_mem[rf[rs] + immediate];
                    $display("lw $%-2d, %-d($%-2d)", rt, immediate, rs);
                end
                6'b101011: begin // sw $rt, offset($rs)
                    data_mem[rf[rs] + immediate] <= rf[rt];
                    $display("sw $%-2d, %-d($%-2d)", rt, immediate, rs);
                end
                6'b000000: begin
                    case (funct)
                        6'b000000: begin // sll  $rd, $rt, shamt
                            rf[rd] <= rf[rt] << shamt;
                            $display("sll $%-2d, $%-2d, $%-d", rd, rt, shamt);
                        end
                        6'b000010: begin // srl  $rd, $rt, shamt
                            rf[rd] <= rf[rt] >> shamt;
                            $display("srl $%-2d, $%-2d, $%-d", rd, rt, shamt);
                        end
                        6'b100000: begin // add $rd, $rs, $rt
                            rf[rd] <= rf[rs] + rf[rt];
                            $display("add $%-2d, $%-2d, $%-2d", rd, rs, rt);
                        end
                        6'b100010: begin // sub $rd, $rs, $rt
                            rf[rd] <= rf[rs] - rf[rt];
                            $display("sub $%-2d, $%-2d, $%-2d", rd, rs, rt);
                        end
                        6'b100001: begin // move $rd, $rs
                            rf[rd] <= rf[rs];
                            $display("move $%-2d, $%-2d", rd, rs);
                        end
                        6'b111111: begin // halt
                            $display("halt");
                        end
                        6'b001111: begin // nop
                            $display("nop");
                        end
                        default: begin
                            $display("Unknown funct: %b", funct);
                        end
                    endcase
                end
                6'b000111: begin // bge $rs, $rt, label
                    if (rf[rs] >= rf[rt]) begin
                        pc <= immediate;
                        $display("bge $%-2d, $%-2d, label", rs, rt);
                    end
                end
                6'b000110: begin // ble $rs, $rt, label
                    if (rf[rs] <= rf[rt]) begin
                        pc <= immediate;
                        $display("ble $%-2d, $%-2d, label", rs, rt);
                    end
                end
                6'b000010: begin // j label
                    pc <= address[7:0];
                    $display("j label %-d", address);
                end
                default: begin
                    $display("Unknown opcode: %b", opcode);
                end
            endcase
        end
    end

endmodule

3-inst-mips/toy-mips-tb.v
`include "toy-mips.v"

module tb_toy_processor;

    reg clk;
    reg reset;
    
    toy_processor uut (
        .clk(clk),
        .reset(reset)
    );

    always #5 clk = ~clk;

    initial begin
        clk = 0;
        reset = 1;

        #20;
        reset = 0;

        wait(uut.instruction == 32'h0000003f);
        #20;

        $display("\n-----------------");
        $display("Data Memory (HEX)");
        $display("-----------------");
        for (integer i = 0; i < 64; i = i + 8) begin
            $display("%-3d: %08h %08h %08h %08h %08h %08h %08h %08h", i,
                uut.data_mem[i], uut.data_mem[i + 1], 
                uut.data_mem[i + 2], uut.data_mem[i + 3],
                uut.data_mem[i + 4], uut.data_mem[i + 5], 
                uut.data_mem[i + 6], uut.data_mem[i + 7]);
        end

        $display("\n-------------------");
        $display("Register File (HEX)");
        $display("-------------------");
        for (integer i = 0; i < 32; i = i + 8) begin
            $display("$%-2d: %08h %08h %08h %08h %08h %08h %08h %08h", i,
                uut.rf[i], uut.rf[i + 1], 
                uut.rf[i + 2], uut.rf[i + 3],
                uut.rf[i + 4], uut.rf[i + 5], 
                uut.rf[i + 6], uut.rf[i + 7]);
        end

        $display("\n-----------------");
        $display("Data Memory (DEC)");
        $display("-----------------");
        for (integer i = 0; i < 64; i = i + 8) begin
            $display("%-3d: %8d %8d %8d %8d %8d %8d %8d %8d", i,
                uut.data_mem[i], uut.data_mem[i + 1], 
                uut.data_mem[i + 2], uut.data_mem[i + 3],
                uut.data_mem[i + 4], uut.data_mem[i + 5], 
                uut.data_mem[i + 6], uut.data_mem[i + 7]);
        end

        $display("\n-------------------");
        $display("Register File (DEC)");
        $display("-------------------");
        for (integer i = 0; i < 32; i = i + 8) begin
            $display("$%-2d: %8d %8d %8d %8d %8d %8d %8d %8d", i,
                uut.rf[i], uut.rf[i + 1], 
                uut.rf[i + 2], uut.rf[i + 3],
                uut.rf[i + 4], uut.rf[i + 5], 
                uut.rf[i + 6], uut.rf[i + 7]);
        end
        reset = 1;
        $display("");
        $finish;
    end

    initial begin
        $readmemh("data_mem.hex", uut.data_mem);
        $readmemh("inst_mem.hex", uut.inst_mem);
        $readmemh("rf.hex", uut.rf);
    end

    always @(posedge clk) begin
        if (reset==0)
            $write("%2d %8h    // ", uut.pc, uut.instruction);
    end

    initial begin
        $dumpfile("toy-mips.vcd");
        $dumpvars(0, tb_toy_processor);
    end

endmodule

3-inst-mips/toy-mips.vcd
$date
	Tue Jun 11 19:01:47 2024
$end
$version
	Icarus Verilog
$end
$timescale
	1s
$end
$scope module tb_toy_processor $end
$var reg 1 ! clk $end
$var reg 1 " reset $end
$scope module uut $end
$var wire 1 ! clk $end
$var wire 32 # instruction [31:0] $end
$var wire 1 " reset $end
$var reg 26 $ address [25:0] $end
$var reg 6 % funct [5:0] $end
$var reg 16 & immediate [15:0] $end
$var reg 6 ' opcode [5:0] $end
$var reg 8 ( pc [7:0] $end
$var reg 5 ) rd [4:0] $end
$var reg 5 * rs [4:0] $end
$var reg 5 + rt [4:0] $end
$var reg 5 , shamt [4:0] $end
$upscope $end
$scope begin $ivl_for_loop0 $end
$var integer 32 - i [31:0] $end
$upscope $end
$scope begin $ivl_for_loop1 $end
$var integer 32 . i [31:0] $end
$upscope $end
$scope begin $ivl_for_loop2 $end
$var integer 32 / i [31:0] $end
$upscope $end
$scope begin $ivl_for_loop3 $end
$var integer 32 0 i [31:0] $end
$upscope $end
$upscope $end
$enddefinitions $end
$comment Show the parameter values. $end
$dumpall
$end
#0
$dumpvars
bx 0
bx /
bx .
bx -
bx ,
bx +
bx *
bx )
b0 (
bx '
bx &
bx %
bx $
b100100000000000000000001100100 #
1"
0!
$end
#5
1!
#10
0!
#15
1!
#20
0!
0"
#25
b100100000000100000000000000001 #
b1 (
b100100 %
b1100100 $
b1100100 &
b1 ,
b0 )
b0 +
b0 *
b1001 '
1!
#30
0!
#35
b100100000000110000000000000000 #
b10 (
b1 %
b100000000000000001 $
b1 &
b0 ,
b10 +
1!
#40
0!
#45
b11000100001100000100000 #
b11 (
b0 %
b110000000000000000 $
b0 &
b11 +
1!
#50
0!
#55
b100000010000100000000000000001 #
b100 (
b100000 %
b11000100001100000100000 $
b1100000100000 &
b11 )
b10 +
b11 *
b0 '
1!
#60
0!
#65
b11000010000000000000000000011 #
b101 (
b1 %
b10000100000000000000001 $
b1 &
b0 )
b10 *
b1000 '
1!
#70
0!
#75
b1111 #
b110 (
b11 %
b10000000000000000000011 $
b11 &
b0 +
b110 '
1!
#80
0!
#85
b11000100001100000100000 #
b11 (
b1111 %
b1111 $
b1111 &
b0 *
b0 '
1!
#90
0!
#95
b100000010000100000000000000001 #
b100 (
b100000 %
b11000100001100000100000 $
b1100000100000 &
b11 )
b10 +
b11 *
1!
#100
0!
#105
b11000010000000000000000000011 #
b101 (
b1 %
b10000100000000000000001 $
b1 &
b0 )
b10 *
b1000 '
1!
#110
0!
#115
b1111 #
b110 (
b11 %
b10000000000000000000011 $
b11 &
b0 +
b110 '
1!
#120
0!
#125
b11000100001100000100000 #
b11 (
b1111 %
b1111 $
b1111 &
b0 *
b0 '
1!
#130
0!
#135
b100000010000100000000000000001 #
b100 (
b100000 %
b11000100001100000100000 $
b1100000100000 &
b11 )
b10 +
b11 *
1!
#140
0!
#145
b11000010000000000000000000011 #
b101 (
b1 %
b10000100000000000000001 $
b1 &
b0 )
b10 *
b1000 '
1!
#150
0!
#155
b1111 #
b110 (
b11 %
b10000000000000000000011 $
b11 &
b0 +
b110 '
1!
#160
0!
#165
b11000100001100000100000 #
b11 (
b1111 %
b1111 $
b1111 &
b0 *
b0 '
1!
#170
0!
#175
b100000010000100000000000000001 #
b100 (
b100000 %
b11000100001100000100000 $
b1100000100000 &
b11 )
b10 +
b11 *
1!
#180
0!
#185
b11000010000000000000000000011 #
b101 (
b1 %
b10000100000000000000001 $
b1 &
b0 )
b10 *
b1000 '
1!
#190
0!
#195
b1111 #
b110 (
b11 %
b10000000000000000000011 $
b11 &
b0 +
b110 '
1!
#200
0!
#205
b11000100001100000100000 #
b11 (
b1111 %
b1111 $
b1111 &
b0 *
b0 '
1!
#210
0!
#215
b100000010000100000000000000001 #
b100 (
b100000 %
b11000100001100000100000 $
b1100000100000 &
b11 )
b10 +
b11 *
1!
#220
0!
#225
b11000010000000000000000000011 #
b101 (
b1 %
b10000100000000000000001 $
b1 &
b0 )
b10 *
b1000 '
1!
#230
0!
#235
b1111 #
b110 (
b11 %
b10000000000000000000011 $
b11 &
b0 +
b110 '
1!
#240
0!
#245
b11000100001100000100000 #
b11 (
b1111 %
b1111 $
b1111 &
b0 *
b0 '
1!
#250
0!
#255
b100000010000100000000000000001 #
b100 (
b100000 %
b11000100001100000100000 $
b1100000100000 &
b11 )
b10 +
b11 *
1!
#260
0!
#265
b11000010000000000000000000011 #
b101 (
b1 %
b10000100000000000000001 $
b1 &
b0 )
b10 *
b1000 '
1!
#270
0!
#275
b1111 #
b110 (
b11 %
b10000000000000000000011 $
b11 &
b0 +
b110 '
1!
#280
0!
#285
b11000100001100000100000 #
b11 (
b1111 %
b1111 $
b1111 &
b0 *
b0 '
1!
#290
0!
#295
b100000010000100000000000000001 #
b100 (
b100000 %
b11000100001100000100000 $
b1100000100000 &
b11 )
b10 +
b11 *
1!
#300
0!
#305
b11000010000000000000000000011 #
b101 (
b1 %
b10000100000000000000001 $
b1 &
b0 )
b10 *
b1000 '
1!
#310
0!
#315
b1111 #
b110 (
b11 %
b10000000000000000000011 $
b11 &
b0 +
b110 '
1!
#320
0!
#325
b11000100001100000100000 #
b11 (
b1111 %
b1111 $
b1111 &
b0 *
b0 '
1!
#330
0!
#335
b100000010000100000000000000001 #
b100 (
b100000 %
b11000100001100000100000 $
b1100000100000 &
b11 )
b10 +
b11 *
1!
#340
0!
#345
b11000010000000000000000000011 #
b101 (
b1 %
b10000100000000000000001 $
b1 &
b0 )
b10 *
b1000 '
1!
#350
0!
#355
b1111 #
b110 (
b11 %
b10000000000000000000011 $
b11 &
b0 +
b110 '
1!
#360
0!
#365
b11000100001100000100000 #
b11 (
b1111 %
b1111 $
b1111 &
b0 *
b0 '
1!
#370
0!
#375
b100000010000100000000000000001 #
b100 (
b100000 %
b11000100001100000100000 $
b1100000100000 &
b11 )
b10 +
b11 *
1!
#380
0!
#385
b11000010000000000000000000011 #
b101 (
b1 %
b10000100000000000000001 $
b1 &
b0 )
b10 *
b1000 '
1!
#390
0!
#395
b1111 #
b110 (
b11 %
b10000000000000000000011 $
b11 &
b0 +
b110 '
1!
#400
0!
#405
b11000100001100000100000 #
b11 (
b1111 %
b1111 $
b1111 &
b0 *
b0 '
1!
#410
0!
#415
b100000010000100000000000000001 #
b100 (
b100000 %
b11000100001100000100000 $
b1100000100000 &
b11 )
b10 +
b11 *
1!
#420
0!
#425
b11000010000000000000000000011 #
b101 (
b1 %
b10000100000000000000001 $
b1 &
b0 )
b10 *
b1000 '
1!
#430
0!
#435
b1111 #
b110 (
b11 %
b10000000000000000000011 $
b11 &
b0 +
b110 '
1!
#440
0!
#445
b11000100001100000100000 #
b11 (
b1111 %
b1111 $
b1111 &
b0 *
b0 '
1!
#450
0!
#455
b100000010000100000000000000001 #
b100 (
b100000 %
b11000100001100000100000 $
b1100000100000 &
b11 )
b10 +
b11 *
1!
#460
0!
#465
b11000010000000000000000000011 #
b101 (
b1 %
b10000100000000000000001 $
b1 &
b0 )
b10 *
b1000 '
1!
#470
0!
#475
b1111 #
b110 (
b11 %
b10000000000000000000011 $
b11 &
b0 +
b110 '
1!
#480
0!
#485
b11000100001100000100000 #
b11 (
b1111 %
b1111 $
b1111 &
b0 *
b0 '
1!
#490
0!
#495
b100000010000100000000000000001 #
b100 (
b100000 %
b11000100001100000100000 $
b1100000100000 &
b11 )
b10 +
b11 *
1!
#500
0!
#505
b11000010000000000000000000011 #
b101 (
b1 %
b10000100000000000000001 $
b1 &
b0 )
b10 *
b1000 '
1!
#510
0!
#515
b1111 #
b110 (
b11 %
b10000000000000000000011 $
b11 &
b0 +
b110 '
1!
#520
0!
#525
b11000100001100000100000 #
b11 (
b1111 %
b1111 $
b1111 &
b0 *
b0 '
1!
#530
0!
#535
b100000010000100000000000000001 #
b100 (
b100000 %
b11000100001100000100000 $
b1100000100000 &
b11 )
b10 +
b11 *
1!
#540
0!
#545
b11000010000000000000000000011 #
b101 (
b1 %
b10000100000000000000001 $
b1 &
b0 )
b10 *
b1000 '
1!
#550
0!
#555
b1111 #
b110 (
b11 %
b10000000000000000000011 $
b11 &
b0 +
b110 '
1!
#560
0!
#565
b11000100001100000100000 #
b11 (
b1111 %
b1111 $
b1111 &
b0 *
b0 '
1!
#570
0!
#575
b100000010000100000000000000001 #
b100 (
b100000 %
b11000100001100000100000 $
b1100000100000 &
b11 )
b10 +
b11 *
1!
#580
0!
#585
b11000010000000000000000000011 #
b101 (
b1 %
b10000100000000000000001 $
b1 &
b0 )
b10 *
b1000 '
1!
#590
0!
#595
b1111 #
b110 (
b11 %
b10000000000000000000011 $
b11 &
b0 +
b110 '
1!
#600
0!
#605
b11000100001100000100000 #
b11 (
b1111 %
b1111 $
b1111 &
b0 *
b0 '
1!
#610
0!
#615
b100000010000100000000000000001 #
b100 (
b100000 %
b11000100001100000100000 $
b1100000100000 &
b11 )
b10 +
b11 *
1!
#620
0!
#625
b11000010000000000000000000011 #
b101 (
b1 %
b10000100000000000000001 $
b1 &
b0 )
b10 *
b1000 '
1!
#630
0!
#635
b1111 #
b110 (
b11 %
b10000000000000000000011 $
b11 &
b0 +
b110 '
1!
#640
0!
#645
b11000100001100000100000 #
b11 (
b1111 %
b1111 $
b1111 &
b0 *
b0 '
1!
#650
0!
#655
b100000010000100000000000000001 #
b100 (
b100000 %
b11000100001100000100000 $
b1100000100000 &
b11 )
b10 +
b11 *
1!
#660
0!
#665
b11000010000000000000000000011 #
b101 (
b1 %
b10000100000000000000001 $
b1 &
b0 )
b10 *
b1000 '
1!
#670
0!
#675
b1111 #
b110 (
b11 %
b10000000000000000000011 $
b11 &
b0 +
b110 '
1!
#680
0!
#685
b11000100001100000100000 #
b11 (
b1111 %
b1111 $
b1111 &
b0 *
b0 '
1!
#690
0!
#695
b100000010000100000000000000001 #
b100 (
b100000 %
b11000100001100000100000 $
b1100000100000 &
b11 )
b10 +
b11 *
1!
#700
0!
#705
b11000010000000000000000000011 #
b101 (
b1 %
b10000100000000000000001 $
b1 &
b0 )
b10 *
b1000 '
1!
#710
0!
#715
b1111 #
b110 (
b11 %
b10000000000000000000011 $
b11 &
b0 +
b110 '
1!
#720
0!
#725
b11000100001100000100000 #
b11 (
b1111 %
b1111 $
b1111 &
b0 *
b0 '
1!
#730
0!
#735
b100000010000100000000000000001 #
b100 (
b100000 %
b11000100001100000100000 $
b1100000100000 &
b11 )
b10 +
b11 *
1!
#740
0!
#745
b11000010000000000000000000011 #
b101 (
b1 %
b10000100000000000000001 $
b1 &
b0 )
b10 *
b1000 '
1!
#750
0!
#755
b1111 #
b110 (
b11 %
b10000000000000000000011 $
b11 &
b0 +
b110 '
1!
#760
0!
#765
b11000100001100000100000 #
b11 (
b1111 %
b1111 $
b1111 &
b0 *
b0 '
1!
#770
0!
#775
b100000010000100000000000000001 #
b100 (
b100000 %
b11000100001100000100000 $
b1100000100000 &
b11 )
b10 +
b11 *
1!
#780
0!
#785
b11000010000000000000000000011 #
b101 (
b1 %
b10000100000000000000001 $
b1 &
b0 )
b10 *
b1000 '
1!
#790
0!
#795
b1111 #
b110 (
b11 %
b10000000000000000000011 $
b11 &
b0 +
b110 '
1!
#800
0!
#805
b11000100001100000100000 #
b11 (
b1111 %
b1111 $
b1111 &
b0 *
b0 '
1!
#810
0!
#815
b100000010000100000000000000001 #
b100 (
b100000 %
b11000100001100000100000 $
b1100000100000 &
b11 )
b10 +
b11 *
1!
#820
0!
#825
b11000010000000000000000000011 #
b101 (
b1 %
b10000100000000000000001 $
b1 &
b0 )
b10 *
b1000 '
1!
#830
0!
#835
b1111 #
b110 (
b11 %
b10000000000000000000011 $
b11 &
b0 +
b110 '
1!
#840
0!
#845
b11000100001100000100000 #
b11 (
b1111 %
b1111 $
b1111 &
b0 *
b0 '
1!
#850
0!
#855
b100000010000100000000000000001 #
b100 (
b100000 %
b11000100001100000100000 $
b1100000100000 &
b11 )
b10 +
b11 *
1!
#860
0!
#865
b11000010000000000000000000011 #
b101 (
b1 %
b10000100000000000000001 $
b1 &
b0 )
b10 *
b1000 '
1!
#870
0!
#875
b1111 #
b110 (
b11 %
b10000000000000000000011 $
b11 &
b0 +
b110 '
1!
#880
0!
#885
b11000100001100000100000 #
b11 (
b1111 %
b1111 $
b1111 &
b0 *
b0 '
1!
#890
0!
#895
b100000010000100000000000000001 #
b100 (
b100000 %
b11000100001100000100000 $
b1100000100000 &
b11 )
b10 +
b11 *
1!
#900
0!
#905
b11000010000000000000000000011 #
b101 (
b1 %
b10000100000000000000001 $
b1 &
b0 )
b10 *
b1000 '
1!
#910
0!
#915
b1111 #
b110 (
b11 %
b10000000000000000000011 $
b11 &
b0 +
b110 '
1!
#920
0!
#925
b11000100001100000100000 #
b11 (
b1111 %
b1111 $
b1111 &
b0 *
b0 '
1!
#930
0!
#935
b100000010000100000000000000001 #
b100 (
b100000 %
b11000100001100000100000 $
b1100000100000 &
b11 )
b10 +
b11 *
1!
#940
0!
#945
b11000010000000000000000000011 #
b101 (
b1 %
b10000100000000000000001 $
b1 &
b0 )
b10 *
b1000 '
1!
#950
0!
#955
b1111 #
b110 (
b11 %
b10000000000000000000011 $
b11 &
b0 +
b110 '
1!
#960
0!
#965
b11000100001100000100000 #
b11 (
b1111 %
b1111 $
b1111 &
b0 *
b0 '
1!
#970
0!
#975
b100000010000100000000000000001 #
b100 (
b100000 %
b11000100001100000100000 $
b1100000100000 &
b11 )
b10 +
b11 *
1!
#980
0!
#985
b11000010000000000000000000011 #
b101 (
b1 %
b10000100000000000000001 $
b1 &
b0 )
b10 *
b1000 '
1!
#990
0!
#995
b1111 #
b110 (
b11 %
b10000000000000000000011 $
b11 &
b0 +
b110 '
1!
#1000
0!
#1005
b11000100001100000100000 #
b11 (
b1111 %
b1111 $
b1111 &
b0 *
b0 '
1!
#1010
0!
#1015
b100000010000100000000000000001 #
b100 (
b100000 %
b11000100001100000100000 $
b1100000100000 &
b11 )
b10 +
b11 *
1!
#1020
0!
#1025
b11000010000000000000000000011 #
b101 (
b1 %
b10000100000000000000001 $
b1 &
b0 )
b10 *
b1000 '
1!
#1030
0!
#1035
b1111 #
b110 (
b11 %
b10000000000000000000011 $
b11 &
b0 +
b110 '
1!
#1040
0!
#1045
b11000100001100000100000 #
b11 (
b1111 %
b1111 $
b1111 &
b0 *
b0 '
1!
#1050
0!
#1055
b100000010000100000000000000001 #
b100 (
b100000 %
b11000100001100000100000 $
b1100000100000 &
b11 )
b10 +
b11 *
1!
#1060
0!
#1065
b11000010000000000000000000011 #
b101 (
b1 %
b10000100000000000000001 $
b1 &
b0 )
b10 *
b1000 '
1!
#1070
0!
#1075
b1111 #
b110 (
b11 %
b10000000000000000000011 $
b11 &
b0 +
b110 '
1!
#1080
0!
#1085
b11000100001100000100000 #
b11 (
b1111 %
b1111 $
b1111 &
b0 *
b0 '
1!
#1090
0!
#1095
b100000010000100000000000000001 #
b100 (
b100000 %
b11000100001100000100000 $
b1100000100000 &
b11 )
b10 +
b11 *
1!
#1100
0!
#1105
b11000010000000000000000000011 #
b101 (
b1 %
b10000100000000000000001 $
b1 &
b0 )
b10 *
b1000 '
1!
#1110
0!
#1115
b1111 #
b110 (
b11 %
b10000000000000000000011 $
b11 &
b0 +
b110 '
1!
#1120
0!
#1125
b11000100001100000100000 #
b11 (
b1111 %
b1111 $
b1111 &
b0 *
b0 '
1!
#1130
0!
#1135
b100000010000100000000000000001 #
b100 (
b100000 %
b11000100001100000100000 $
b1100000100000 &
b11 )
b10 +
b11 *
1!
#1140
0!
#1145
b11000010000000000000000000011 #
b101 (
b1 %
b10000100000000000000001 $
b1 &
b0 )
b10 *
b1000 '
1!
#1150
0!
#1155
b1111 #
b110 (
b11 %
b10000000000000000000011 $
b11 &
b0 +
b110 '
1!
#1160
0!
#1165
b11000100001100000100000 #
b11 (
b1111 %
b1111 $
b1111 &
b0 *
b0 '
1!
#1170
0!
#1175
b100000010000100000000000000001 #
b100 (
b100000 %
b11000100001100000100000 $
b1100000100000 &
b11 )
b10 +
b11 *
1!
#1180
0!
#1185
b11000010000000000000000000011 #
b101 (
b1 %
b10000100000000000000001 $
b1 &
b0 )
b10 *
b1000 '
1!
#1190
0!
#1195
b1111 #
b110 (
b11 %
b10000000000000000000011 $
b11 &
b0 +
b110 '
1!
#1200
0!
#1205
b11000100001100000100000 #
b11 (
b1111 %
b1111 $
b1111 &
b0 *
b0 '
1!
#1210
0!
#1215
b100000010000100000000000000001 #
b100 (
b100000 %
b11000100001100000100000 $
b1100000100000 &
b11 )
b10 +
b11 *
1!
#1220
0!
#1225
b11000010000000000000000000011 #
b101 (
b1 %
b10000100000000000000001 $
b1 &
b0 )
b10 *
b1000 '
1!
#1230
0!
#1235
b1111 #
b110 (
b11 %
b10000000000000000000011 $
b11 &
b0 +
b110 '
1!
#1240
0!
#1245
b11000100001100000100000 #
b11 (
b1111 %
b1111 $
b1111 &
b0 *
b0 '
1!
#1250
0!
#1255
b100000010000100000000000000001 #
b100 (
b100000 %
b11000100001100000100000 $
b1100000100000 &
b11 )
b10 +
b11 *
1!
#1260
0!
#1265
b11000010000000000000000000011 #
b101 (
b1 %
b10000100000000000000001 $
b1 &
b0 )
b10 *
b1000 '
1!
#1270
0!
#1275
b1111 #
b110 (
b11 %
b10000000000000000000011 $
b11 &
b0 +
b110 '
1!
#1280
0!
#1285
b11000100001100000100000 #
b11 (
b1111 %
b1111 $
b1111 &
b0 *
b0 '
1!
#1290
0!
#1295
b100000010000100000000000000001 #
b100 (
b100000 %
b11000100001100000100000 $
b1100000100000 &
b11 )
b10 +
b11 *
1!
#1300
0!
#1305
b11000010000000000000000000011 #
b101 (
b1 %
b10000100000000000000001 $
b1 &
b0 )
b10 *
b1000 '
1!
#1310
0!
#1315
b1111 #
b110 (
b11 %
b10000000000000000000011 $
b11 &
b0 +
b110 '
1!
#1320
0!
#1325
b11000100001100000100000 #
b11 (
b1111 %
b1111 $
b1111 &
b0 *
b0 '
1!
#1330
0!
#1335
b100000010000100000000000000001 #
b100 (
b100000 %
b11000100001100000100000 $
b1100000100000 &
b11 )
b10 +
b11 *
1!
#1340
0!
#1345
b11000010000000000000000000011 #
b101 (
b1 %
b10000100000000000000001 $
b1 &
b0 )
b10 *
b1000 '
1!
#1350
0!
#1355
b1111 #
b110 (
b11 %
b10000000000000000000011 $
b11 &
b0 +
b110 '
1!
#1360
0!
#1365
b11000100001100000100000 #
b11 (
b1111 %
b1111 $
b1111 &
b0 *
b0 '
1!
#1370
0!
#1375
b100000010000100000000000000001 #
b100 (
b100000 %
b11000100001100000100000 $
b1100000100000 &
b11 )
b10 +
b11 *
1!
#1380
0!
#1385
b11000010000000000000000000011 #
b101 (
b1 %
b10000100000000000000001 $
b1 &
b0 )
b10 *
b1000 '
1!
#1390
0!
#1395
b1111 #
b110 (
b11 %
b10000000000000000000011 $
b11 &
b0 +
b110 '
1!
#1400
0!
#1405
b11000100001100000100000 #
b11 (
b1111 %
b1111 $
b1111 &
b0 *
b0 '
1!
#1410
0!
#1415
b100000010000100000000000000001 #
b100 (
b100000 %
b11000100001100000100000 $
b1100000100000 &
b11 )
b10 +
b11 *
1!
#1420
0!
#1425
b11000010000000000000000000011 #
b101 (
b1 %
b10000100000000000000001 $
b1 &
b0 )
b10 *
b1000 '
1!
#1430
0!
#1435
b1111 #
b110 (
b11 %
b10000000000000000000011 $
b11 &
b0 +
b110 '
1!
#1440
0!
#1445
b11000100001100000100000 #
b11 (
b1111 %
b1111 $
b1111 &
b0 *
b0 '
1!
#1450
0!
#1455
b100000010000100000000000000001 #
b100 (
b100000 %
b11000100001100000100000 $
b1100000100000 &
b11 )
b10 +
b11 *
1!
#1460
0!
#1465
b11000010000000000000000000011 #
b101 (
b1 %
b10000100000000000000001 $
b1 &
b0 )
b10 *
b1000 '
1!
#1470
0!
#1475
b1111 #
b110 (
b11 %
b10000000000000000000011 $
b11 &
b0 +
b110 '
1!
#1480
0!
#1485
b11000100001100000100000 #
b11 (
b1111 %
b1111 $
b1111 &
b0 *
b0 '
1!
#1490
0!
#1495
b100000010000100000000000000001 #
b100 (
b100000 %
b11000100001100000100000 $
b1100000100000 &
b11 )
b10 +
b11 *
1!
#1500
0!
#1505
b11000010000000000000000000011 #
b101 (
b1 %
b10000100000000000000001 $
b1 &
b0 )
b10 *
b1000 '
1!
#1510
0!
#1515
b1111 #
b110 (
b11 %
b10000000000000000000011 $
b11 &
b0 +
b110 '
1!
#1520
0!
#1525
b11000100001100000100000 #
b11 (
b1111 %
b1111 $
b1111 &
b0 *
b0 '
1!
#1530
0!
#1535
b100000010000100000000000000001 #
b100 (
b100000 %
b11000100001100000100000 $
b1100000100000 &
b11 )
b10 +
b11 *
1!
#1540
0!
#1545
b11000010000000000000000000011 #
b101 (
b1 %
b10000100000000000000001 $
b1 &
b0 )
b10 *
b1000 '
1!
#1550
0!
#1555
b1111 #
b110 (
b11 %
b10000000000000000000011 $
b11 &
b0 +
b110 '
1!
#1560
0!
#1565
b11000100001100000100000 #
b11 (
b1111 %
b1111 $
b1111 &
b0 *
b0 '
1!
#1570
0!
#1575
b100000010000100000000000000001 #
b100 (
b100000 %
b11000100001100000100000 $
b1100000100000 &
b11 )
b10 +
b11 *
1!
#1580
0!
#1585
b11000010000000000000000000011 #
b101 (
b1 %
b10000100000000000000001 $
b1 &
b0 )
b10 *
b1000 '
1!
#1590
0!
#1595
b1111 #
b110 (
b11 %
b10000000000000000000011 $
b11 &
b0 +
b110 '
1!
#1600
0!
#1605
b11000100001100000100000 #
b11 (
b1111 %
b1111 $
b1111 &
b0 *
b0 '
1!
#1610
0!
#1615
b100000010000100000000000000001 #
b100 (
b100000 %
b11000100001100000100000 $
b1100000100000 &
b11 )
b10 +
b11 *
1!
#1620
0!
#1625
b11000010000000000000000000011 #
b101 (
b1 %
b10000100000000000000001 $
b1 &
b0 )
b10 *
b1000 '
1!
#1630
0!
#1635
b1111 #
b110 (
b11 %
b10000000000000000000011 $
b11 &
b0 +
b110 '
1!
#1640
0!
#1645
b11000100001100000100000 #
b11 (
b1111 %
b1111 $
b1111 &
b0 *
b0 '
1!
#1650
0!
#1655
b100000010000100000000000000001 #
b100 (
b100000 %
b11000100001100000100000 $
b1100000100000 &
b11 )
b10 +
b11 *
1!
#1660
0!
#1665
b11000010000000000000000000011 #
b101 (
b1 %
b10000100000000000000001 $
b1 &
b0 )
b10 *
b1000 '
1!
#1670
0!
#1675
b1111 #
b110 (
b11 %
b10000000000000000000011 $
b11 &
b0 +
b110 '
1!
#1680
0!
#1685
b11000100001100000100000 #
b11 (
b1111 %
b1111 $
b1111 &
b0 *
b0 '
1!
#1690
0!
#1695
b100000010000100000000000000001 #
b100 (
b100000 %
b11000100001100000100000 $
b1100000100000 &
b11 )
b10 +
b11 *
1!
#1700
0!
#1705
b11000010000000000000000000011 #
b101 (
b1 %
b10000100000000000000001 $
b1 &
b0 )
b10 *
b1000 '
1!
#1710
0!
#1715
b1111 #
b110 (
b11 %
b10000000000000000000011 $
b11 &
b0 +
b110 '
1!
#1720
0!
#1725
b11000100001100000100000 #
b11 (
b1111 %
b1111 $
b1111 &
b0 *
b0 '
1!
#1730
0!
#1735
b100000010000100000000000000001 #
b100 (
b100000 %
b11000100001100000100000 $
b1100000100000 &
b11 )
b10 +
b11 *
1!
#1740
0!
#1745
b11000010000000000000000000011 #
b101 (
b1 %
b10000100000000000000001 $
b1 &
b0 )
b10 *
b1000 '
1!
#1750
0!
#1755
b1111 #
b110 (
b11 %
b10000000000000000000011 $
b11 &
b0 +
b110 '
1!
#1760
0!
#1765
b11000100001100000100000 #
b11 (
b1111 %
b1111 $
b1111 &
b0 *
b0 '
1!
#1770
0!
#1775
b100000010000100000000000000001 #
b100 (
b100000 %
b11000100001100000100000 $
b1100000100000 &
b11 )
b10 +
b11 *
1!
#1780
0!
#1785
b11000010000000000000000000011 #
b101 (
b1 %
b10000100000000000000001 $
b1 &
b0 )
b10 *
b1000 '
1!
#1790
0!
#1795
b1111 #
b110 (
b11 %
b10000000000000000000011 $
b11 &
b0 +
b110 '
1!
#1800
0!
